MJCalc/__init__.py
MJCalc-0.1.dist-info/LICENSE
MJCalc-0.1.dist-info/METADATA
MJCalc-0.1.dist-info/WHEEL
MJCalc-0.1.dist-info/top_level.txt
MJCalc-0.1.dist-info/RECORD
